yarc/__init__.py
yarc/app.py
yarc/launch.py
yarc/util.py
yarc/ws.py
yarc/static/resources/backspace.svg
yarc/static/resources/brightness.svg
yarc/static/resources/fullscreen.svg
yarc/static/resources/keypress_sound.mp3
yarc/static/resources/left-mouse-button-click.mp3
yarc/static/resources/mute.svg
yarc/static/resources/right-mouse-button-click.mp3
yarc/static/scripts/remote.js
yarc/static/styles/remote.css
yarc/templates/remote.html
yarc_server-0.1.1.dist-info/LICENSE
yarc_server-0.1.1.dist-info/METADATA
yarc_server-0.1.1.dist-info/WHEEL
yarc_server-0.1.1.dist-info/entry_points.txt
yarc_server-0.1.1.dist-info/top_level.txt
yarc_server-0.1.1.dist-info/RECORD
