Metadata-Version: 2.1
Name: yarc-server
Version: 0.1.1
Summary: Yet Another Remote Control
Home-page: https://github.com/return007/yarc
Author: return007
Author-email: glalchandanig@gmail.com
License: MIT
Platform: UNKNOWN
Classifier: License :: OSI Approved :: MIT License
Classifier: Development Status :: 3 - Alpha
Classifier: Topic :: Internet :: WWW/HTTP :: HTTP Servers
Classifier: Programming Language :: Python :: 3
Requires-Python: >=3.6
Requires-Dist: asyncio
Requires-Dist: flask
Requires-Dist: pyautogui
Requires-Dist: qrcode
Requires-Dist: websockets
